actava/__init__.py
actava/_alias.py
actava/config.py
actava/deploy/__init__.py
actava/deploy/manifest.py
actava/deploy/package.py
actava/graph/__init__.py
actava/graph/export.py
actava/graph/schema.py
actava/integrations/__init__.py
actava/integrations/langsmith.py
actava/langchain/__init__.py
actava/langchain/chat_models.py
actava/langchain_openai/__init__.py
actava/langgraph/__init__.py
actava/langgraph/checkpoint/__init__.py
actava/langgraph/checkpoint/memory.py
actava/langgraph/prebuilt/__init__.py
actava/runtime/__init__.py
actava/runtime/service.py
actava/telemetry/__init__.py
actava/telemetry/callbacks.py
actava/telemetry/redact.py
actava-0.1.1.dist-info/METADATA
actava-0.1.1.dist-info/WHEEL
actava-0.1.1.dist-info/RECORD
